LICENSE
MANIFEST.in
README.rst
requirements.txt
setup.cfg
setup.py
welut/__init__.py
welut/admin.py
welut/converter.py
welut/converter_backup.py
welut/models.py
welut/settings.py
welut.egg-info/PKG-INFO
welut.egg-info/SOURCES.txt
welut.egg-info/dependency_links.txt
welut.egg-info/not-zip-safe
welut.egg-info/requires.txt
welut.egg-info/top_level.txt
welut/migrations/0001_initial.py
welut/migrations/__init__.py