Metadata-Version: 1.1
Name: welut
Version: 1.0.4
Summary: Welut is a ebook converter
Home-page: https://github.com/agusmakmun/welut
Author: Agus Makmun (Summon Agus)
Author-email: agus@python.web.id
License: MIT
Download-URL: https://github.com/agusmakmun/welut/tarball/v1.0.4
Keywords: welut
Platform: UNKNOWN
Classifier: Framework :: Django
Classifier: Framework :: Django :: 1.8
Classifier: Framework :: Django :: 1.9
Classifier: Framework :: Django :: 1.10
Classifier: Framework :: Django :: 1.11
Classifier: Intended Audience :: Developers
Classifier: Operating System :: OS Independent
Classifier: Programming Language :: Python
Classifier: Programming Language :: Python :: 2.7
Classifier: Programming Language :: Python :: 3.3
Classifier: Programming Language :: Python :: 3.5
Classifier: Development Status :: 5 - Production/Stable
Classifier: Topic :: Software Development :: Libraries :: Python Modules
Classifier: License :: OSI Approved :: MIT License
Classifier: Environment :: Web Environment
